lammps_mol_inserter/__init__.py
lammps_mol_inserter/io.py
lammps_mol_inserter/methods.py
lammps_mol_inserter-0.1.dist-info/licenses/LICENCE
lammps_mol_inserter-0.1.dist-info/METADATA
lammps_mol_inserter-0.1.dist-info/WHEEL
lammps_mol_inserter-0.1.dist-info/top_level.txt
lammps_mol_inserter-0.1.dist-info/RECORD
