Metadata-Version: 2.4
Name: lammps_mol_inserter
Version: 0.1
Summary: Library for inserting molecules into LAMMPS simulation boxes
Home-page: https://github.com/silentdan44/LAMMPS-Molecule-Inserter
Author: Danis Bekmansurov
Author-email: riodan44a@gmail.com
License: MIT
Classifier: License :: OSI Approved :: MIT License
License-File: LICENCE
Requires-Dist: numpy
Requires-Dist: ase
Requires-Dist: lammps
Dynamic: author
Dynamic: author-email
Dynamic: classifier
Dynamic: description
Dynamic: description-content-type
Dynamic: home-page
Dynamic: license
Dynamic: license-file
Dynamic: requires-dist
Dynamic: summary
